{"base-timestamp":1658181124495,"instant":"2022-07-18T14:52:24","log":[
{"device":"<reset>","data":{},"servertime":1658181124495},
{"device":"Heartbeat","data":{"beat":{"value":1.0,"vartime":1658181143495},"logsize":{"value":0,"vartime":1658181143495},"devicetime":1658181143495},"servertime":1658181143495},
{"device":"Heartbeat","data":{"beat":{"value":10.0,"vartime":1658181144495},"logsize":{"value":0,"vartime":1658181144495},"devicetime":1658181144495},"servertime":1658181144495},
{"device":"Heartbeat","data":{"beat":{"value":1.0,"vartime":1658181145495},"logsize":{"value":0,"vartime":1658181145495},"devicetime":1658181145495},"servertime":1658181145495},
{"device":"Heartbeat","data":{"beat":{"value":1.0,"vartime":1658181146495},"logsize":{"value":0,"vartime":1658181146495},"devicetime":1658181146495},"servertime":1658181146495},
{"device":"Heartbeat","data":{"beat":{"value":1.0,"vartime":1658181147495},"logsize":{"value":0,"vartime":1658181147495},"devicetime":1658181147495},"servertime":1658181147495},
{"device":"Heartbeat","data":{"beat":{"value":1.0,"vartime":1658181148495},"logsize":{"value":0,"vartime":1658181148495},"devicetime":1658181148495},"servertime":1658181148495},
{"device":"Heartbeat","data":{"beat":{"value":1.0,"vartime":1658181149495},"logsize":{"value":0,"vartime":1658181149495},"devicetime":1658181149495},"servertime":1658181149495},
{"device":"Login","data":{"observer":{"value":"SYSTEM","vartime":1658181150029},"ip":{"value":"0:0:0:0:0:0:0:1","vartime":1658181150029},"admin":{"value":1,"vartime":1658181150029},"text":{"value":"(admin)","vartime":1658181150029},"devicetime":1658181150029},"servertime":1658181150029},
{"device":"Heartbeat","data":{"beat":{"value":1.0,"vartime":1658181150495},"logsize":{"value":0,"vartime":1658181150495},"devicetime":1658181150495},"servertime":1658181150495},
{"device":"Heartbeat","data":{"beat":{"value":1.0,"vartime":1658181151495},"logsize":{"value":0,"vartime":1658181151495},"devicetime":1658181151495},"servertime":1658181151495},
{"device":"Heartbeat","data":{"beat":{"value":1.0,"vartime":1658181152495},"logsize":{"value":0,"vartime":1658181152495},"devicetime":1658181152495},"servertime":1658181152495},
{"device":"Heartbeat","data":{"beat":{"value":1.0,"vartime":1658181153495},"logsize":{"value":0,"vartime":1658181153495},"devicetime":1658181153495},"servertime":1658181153495},
{"device":"Heartbeat","data":{"beat":{"value":10.0,"vartime":1658181154495},"logsize":{"value":0,"vartime":1658181154495},"devicetime":1658181154495},"servertime":1658181154495},
{"device":"Heartbeat","data":{"beat":{"value":1.0,"vartime":1658181155495},"logsize":{"value":0,"vartime":1658181155495},"devicetime":1658181155495},"servertime":1658181155495},
{"device":"Heartbeat","data":{"beat":{"value":1.0,"vartime":1658181156495},"logsize":{"value":0,"vartime":1658181156495},"devicetime":1658181156495},"servertime":1658181156495},
{"device":"Heartbeat","data":{"beat":{"value":1.0,"vartime":1658181157495},"logsize":{"value":0,"vartime":1658181157495},"devicetime":1658181157495},"servertime":1658181157495},
{"device":"Heartbeat","data":{"beat":{"value":1.0,"vartime":1658181158495},"logsize":{"value":0,"vartime":1658181158495},"devicetime":1658181158495},"servertime":1658181158495},
{"device":"Heartbeat","data":{"beat":{"value":1.0,"vartime":1658181159495},"logsize":{"value":0,"vartime":1658181159495},"devicetime":1658181159495},"servertime":1658181159495},
{"device":"Heartbeat","data":{"beat":{"value":1.0,"vartime":1658181160495},"logsize":{"value":0,"vartime":1658181160495},"devicetime":1658181160495},"servertime":1658181160495},
{"device":"Heartbeat","data":{"beat":{"value":1.0,"vartime":1658181161495},"logsize":{"value":0,"vartime":1658181161495},"devicetime":1658181161495},"servertime":1658181161495},
{"device":"Heartbeat","data":{"beat":{"value":1.0,"vartime":1658181162495},"logsize":{"value":0,"vartime":1658181162495},"devicetime":1658181162495},"servertime":1658181162495},
